server_side_matomo/__init__.py
server_side_matomo/middleware.py
server_side_matomo/tasks.py
server_side_matomo/tests.py
django_server_side_matomo-2.1.0.dist-info/LICENSE
django_server_side_matomo-2.1.0.dist-info/WHEEL
django_server_side_matomo-2.1.0.dist-info/METADATA
django_server_side_matomo-2.1.0.dist-info/RECORD
