Metadata-Version: 2.1
Name: django-server-side-matomo
Version: 2.1.0
Summary: Send analytics data to Matomo using celery
Home-page: https://gitlab.com/burke-software/django-server-side-matomo
Author: David Burke
Author-email: david@burkesoftware.com
Requires-Python: >=3.6,<4.0
Classifier: Framework :: Django
Classifier: Programming Language :: Python :: 3
Classifier: Programming Language :: Python :: 3.6
Classifier: Programming Language :: Python :: 3.7
Classifier: Programming Language :: Python :: 3.8
Requires-Dist: Django (>=1.11)
Requires-Dist: celery[redis] (>=4.1.0)
Requires-Dist: django-ipware (>=2.1.0)
Requires-Dist: piwikapi (>=0.3)
